auth_backend_pam/__init__.py
auth_backend_pam/admin.py
auth_backend_pam/apps.py
auth_backend_pam/backends.py
auth_backend_pam/models.py
auth_backend_pam/urls.py
auth_backend_pam/views.py
auth_backend_pam/migrations/__init__.py
auth_backend_pam/static/css/auth_backend_pam.css
auth_backend_pam/static/js/auth_backend_pam.js
auth_backend_pam/templates/auth_backend_pam/base.html
django_auth_backend_pam-0.1.0.dist-info/AUTHORS.rst
django_auth_backend_pam-0.1.0.dist-info/LICENSE
django_auth_backend_pam-0.1.0.dist-info/METADATA
django_auth_backend_pam-0.1.0.dist-info/WHEEL
django_auth_backend_pam-0.1.0.dist-info/top_level.txt
django_auth_backend_pam-0.1.0.dist-info/RECORD
