Metadata-Version: 2.1
Name: django-auth-backend-pam
Version: 0.1.0
Summary: Django pam auth
Home-page: https://github.com/dcopm999/django-auth-backend-pam
Author: Pavel Tanchev
Author-email: dcopm999@gmail.com
License: MIT
Keywords: django-auth-backend-pam
Platform: UNKNOWN
Classifier: Development Status :: 3 - Alpha
Classifier: Framework :: Django :: 4.0
Classifier: Framework :: Django :: 3.2
Classifier: Framework :: Django :: 2.2
Classifier: Intended Audience :: Developers
Classifier: License :: OSI Approved :: BSD License
Classifier: Natural Language :: English
Classifier: Programming Language :: Python :: 3
Classifier: Programming Language :: Python :: 3.8
Classifier: Programming Language :: Python :: 3.9
Classifier: Programming Language :: Python :: 3.10
License-File: LICENSE
License-File: AUTHORS.rst
Requires-Dist: Django (<4.1,>=2.2)
Requires-Dist: python-pam (==1.8.4)
